adminita/__init__.py
adminita/apps.py
adminita/context_processors.py
adminita/utils.py
adminita/static/adminita/action-fix.css
adminita/static/adminita/adminita-tailwind.css
adminita/static/adminita/adminita-tailwind.js
adminita/static/css/output.css
adminita/static/src/input.css
adminita/templates/admin/actions.html
adminita/templates/admin/app_index.html
adminita/templates/admin/base.html
adminita/templates/admin/change_form.html
adminita/templates/admin/change_list.html
adminita/templates/admin/change_list_results.html
adminita/templates/admin/delete_confirmation.html
adminita/templates/admin/delete_selected_confirmation.html
adminita/templates/admin/filter.html
adminita/templates/admin/index.html
adminita/templates/admin/logged_out.html
adminita/templates/admin/login.html
adminita/templates/admin/object_history.html
adminita/templates/admin/password_change_done.html
adminita/templates/admin/password_change_form.html
adminita/templates/admin/popup_response.html
adminita/templates/admin/submit_line.html
adminita/templates/admin/edit_inline/stacked.html
adminita/templates/admin/edit_inline/tabular.html
adminita/templates/admin/includes/fieldset.html
adminita/templatetags/__init__.py
adminita/templatetags/adminita_tags.py
adminita-0.1.11.dist-info/licenses/LICENSE.md
adminita-0.1.11.dist-info/METADATA
adminita-0.1.11.dist-info/WHEEL
adminita-0.1.11.dist-info/top_level.txt
adminita-0.1.11.dist-info/RECORD
